ppviz.py
ppviz-0.2.0.dist-info/LICENSE
ppviz-0.2.0.dist-info/METADATA
ppviz-0.2.0.dist-info/WHEEL
ppviz-0.2.0.dist-info/entry_points.txt
ppviz-0.2.0.dist-info/RECORD
